retaped_tui/__init__.py
retaped_tui/aboutRT-tui.txt
retaped_tui/globals.py
retaped_tui/login.py
retaped_tui/main.py
retaped_tui/structures.py
retaped_tui/widgets.py
retaped_tui/npyscreen/__init__.py
retaped_tui/npyscreen/apNPSApplication.py
retaped_tui/npyscreen/apNPSApplicationAdvanced.py
retaped_tui/npyscreen/apNPSApplicationEvents.py
retaped_tui/npyscreen/apNPSApplicationManaged.py
retaped_tui/npyscreen/apOptions.py
retaped_tui/npyscreen/eveventhandler.py
retaped_tui/npyscreen/fmActionForm.py
retaped_tui/npyscreen/fmActionFormV2.py
retaped_tui/npyscreen/fmFileSelector.py
retaped_tui/npyscreen/fmForm.py
retaped_tui/npyscreen/fmFormMultiPage.py
retaped_tui/npyscreen/fmFormMutt.py
retaped_tui/npyscreen/fmFormMuttActive.py
retaped_tui/npyscreen/fmFormWithMenus.py
retaped_tui/npyscreen/fmPopup.py
retaped_tui/npyscreen/fm_form_edit_loop.py
retaped_tui/npyscreen/globals.py
retaped_tui/npyscreen/muMenu.py
retaped_tui/npyscreen/muNewMenu.py
retaped_tui/npyscreen/npysGlobalOptions.py
retaped_tui/npyscreen/npysNPSFilteredData.py
retaped_tui/npyscreen/npysThemeManagers.py
retaped_tui/npyscreen/npysThemes.py
retaped_tui/npyscreen/npysTree.py
retaped_tui/npyscreen/npyspmfuncs.py
retaped_tui/npyscreen/npyssafewrapper.py
retaped_tui/npyscreen/proto_fm_screen_area.py
retaped_tui/npyscreen/stdfmemail.py
retaped_tui/npyscreen/utilNotify.py
retaped_tui/npyscreen/util_viewhelp.py
retaped_tui/npyscreen/wgFormControlCheckbox.py
retaped_tui/npyscreen/wgNMenuDisplay.py
retaped_tui/npyscreen/wgannotatetextbox.py
retaped_tui/npyscreen/wgautocomplete.py
retaped_tui/npyscreen/wgboxwidget.py
retaped_tui/npyscreen/wgbutton.py
retaped_tui/npyscreen/wgcheckbox.py
retaped_tui/npyscreen/wgcombobox.py
retaped_tui/npyscreen/wgdatecombo.py
retaped_tui/npyscreen/wgeditmultiline.py
retaped_tui/npyscreen/wgfilenamecombo.py
retaped_tui/npyscreen/wggrid.py
retaped_tui/npyscreen/wggridcoltitles.py
retaped_tui/npyscreen/wgmonthbox.py
retaped_tui/npyscreen/wgmultiline.py
retaped_tui-1.0rc11.dist-info/METADATA
retaped_tui-1.0rc11.dist-info/WHEEL
retaped_tui-1.0rc11.dist-info/entry_points.txt
retaped_tui-1.0rc11.dist-info/licenses/LICENSE
retaped_tui-1.0rc11.dist-info/RECORD
