Metadata-Version: 2.1
Name: retaped_tui
Version: 1.0rc11
Summary: A Revolt client for the terminal
Project-URL: Homepage, https://github.com/error-404-null-not-found/Retaped-tui
Project-URL: Bug Tracker, https://github.com/error-404-null-not-found/Retaped-tui/issues
Author-email: Tetra Green <giggabyte6@gmail.com>
License-File: LICENSE
Classifier: Operating System :: OS Independent
Classifier: Programming Language :: Python :: 3
Requires-Python: >=3.10
Requires-Dist: pyaml
Requires-Dist: requests
Requires-Dist: websockets
